clip/__init__.py
clip/clip.py
clip/model.py
clip/simple_tokenizer.py
utils/__init__.py
utils/processing.py
utils/visualize.py
clip_cam-0.1.5.dist-info/LICENSE
clip_cam-0.1.5.dist-info/METADATA
clip_cam-0.1.5.dist-info/WHEEL
clip_cam-0.1.5.dist-info/top_level.txt
clip_cam-0.1.5.dist-info/RECORD
