Metadata-Version: 2.1
Name: clip_cam
Version: 0.1.5
Summary: A package for visualizing the prompt-image feature matching in ViT-based CLIP models, highlighting the alignment between image features and textual prompts.
Home-page: https://github.com/adityagandhamal/clip_cam
Author: Aditya Gandhamal, Aniruddh Sikdar
Author-email: 
License: MIT
Classifier: Programming Language :: Python :: 3
Classifier: License :: OSI Approved :: MIT License
Classifier: Operating System :: OS Independent
Requires-Python: >=3.6
License-File: LICENSE
Requires-Dist: torch
Requires-Dist: numpy
Requires-Dist: einops
Requires-Dist: opencv-python
Requires-Dist: matplotlib
Requires-Dist: Pillow
Requires-Dist: open-clip-torch ==2.29.0
